alminer/__init__.py
alminer/alminer.py
alminer/constants.py
alminer/version.py
alminer-0.1.3.dist-info/LICENSE
alminer-0.1.3.dist-info/METADATA
alminer-0.1.3.dist-info/WHEEL
alminer-0.1.3.dist-info/top_level.txt
alminer-0.1.3.dist-info/RECORD
