Metadata-Version: 2.1
Name: alminer
Version: 0.1.3
Summary: ALminer: ALMA archive mining and visualization toolkit
Home-page: https://github.com/emerge-erc/ALminer
Author: Aida Ahmadi
Author-email: aahmadi@strw.leidenuniv.nl
License: MIT
Project-URL: Bug Tracker, https://github.com/emerge-erc/ALminer/issues
Classifier: Programming Language :: Python :: 3
Classifier: License :: OSI Approved :: MIT License
Classifier: Operating System :: OS Independent
Requires-Python: >=3.6
License-File: LICENSE
Requires-Dist: numpy (>=1.15)
Requires-Dist: pandas (>1.0)
Requires-Dist: matplotlib (>=3.3.0)
Requires-Dist: pyvo (==1.2.1)
Requires-Dist: astropy (>=3.1.2)
Requires-Dist: astroquery (>=0.4.2)
